jsoncomparison/__init__.py
jsoncomparison/compare.py
jsoncomparison/config.py
jsoncomparison/errors.py
jsoncomparison/ignore.py
tests/__init__.py
tests/test_compare.py
tests/test_config.py
tests/test_ignore.py
jsoncomparison-0.1.1.dist-info/LICENSE
jsoncomparison-0.1.1.dist-info/METADATA
jsoncomparison-0.1.1.dist-info/WHEEL
jsoncomparison-0.1.1.dist-info/top_level.txt
jsoncomparison-0.1.1.dist-info/RECORD
