Metadata-Version: 2.1
Name: jsoncomparison
Version: 0.1.1
Summary: JSON comparator
Home-page: https://github.com/rugleb/jsoncomparison
Author: Gleb Karpushkin
Author-email: rugleb@gmail.com
License: UNKNOWN
Platform: UNKNOWN
Classifier: Programming Language :: Python :: 3
Classifier: License :: OSI Approved :: MIT License
Classifier: Operating System :: OS Independent
